[
    {
        "Gameweek 1": "Regular Season - 1",
        "Gameweek 2": "Regular Season - 2",
        "Gameweek 3": "Regular Season - 3",
        "Gameweek 4": "Regular Season - 4",
        "Gameweek 5": "Regular Season - 5",
        "Gameweek 6": "Regular Season - 6",
        "Gameweek 7": "Regular Season - 7",
        "Gameweek 8": "Regular Season - 8",
        "Gameweek 9": "Regular Season - 9",
        "Gameweek 10": "Regular Season - 10",
        "Gameweek 11": "Regular Season - 11",
        "Gameweek 12": "Regular Season - 12",
        "Gameweek 13": "Regular Season - 13",
        "Gameweek 14": "Regular Season - 14",
        "Gameweek 15": "Regular Season - 15",
        "Gameweek 16": "Regular Season - 16",
        "Gameweek 17": "Regular Season - 17",
        "Gameweek 18": "Regular Season - 18",
        "Gameweek 19": "Regular Season - 19",
        "Gameweek 20": "Regular Season - 20",
        "Gameweek 21": "Regular Season - 21",
        "Gameweek 22": "Regular Season - 22",
        "Gameweek 23": "Regular Season - 23",
        "Gameweek 24": "Regular Season - 24",
        "Gameweek 25": "Regular Season - 25",
        "Gameweek 26": "Regular Season - 26",
        "Gameweek 27": "Regular Season - 27",
        "Gameweek 28": "Regular Season - 28",
        "Gameweek 29": "Regular Season - 29",
        "Gameweek 30": "Regular Season - 30",
        "Gameweek 31": "Regular Season - 31",
        "Gameweek 32": "Regular Season - 32",
        "Gameweek 33": "Regular Season - 33",
        "Gameweek 34": "Regular Season - 34",
        "Gameweek 35": "Regular Season - 35",
        "Gameweek 36": "Regular Season - 36",
        "Gameweek 37": "Regular Season - 37",
        "Gameweek 38": "Regular Season - 38"
    },
    {
        "Regular Season - 1": "Gameweek 1",
        "Regular Season - 2": "Gameweek 2",
        "Regular Season - 3": "Gameweek 3",
        "Regular Season - 4": "Gameweek 4",
        "Regular Season - 5": "Gameweek 5",
        "Regular Season - 6": "Gameweek 6",
        "Regular Season - 7": "Gameweek 7",
        "Regular Season - 8": "Gameweek 8",
        "Regular Season - 9": "Gameweek 9",
        "Regular Season - 10": "Gameweek 10",
        "Regular Season - 11": "Gameweek 11",
        "Regular Season - 12": "Gameweek 12",
        "Regular Season - 13": "Gameweek 13",
        "Regular Season - 14": "Gameweek 14",
        "Regular Season - 15": "Gameweek 15",
        "Regular Season - 16": "Gameweek 16",
        "Regular Season - 17": "Gameweek 17",
        "Regular Season - 18": "Gameweek 18",
        "Regular Season - 19": "Gameweek 19",
        "Regular Season - 20": "Gameweek 20",
        "Regular Season - 21": "Gameweek 21",
        "Regular Season - 22": "Gameweek 22",
        "Regular Season - 23": "Gameweek 23",
        "Regular Season - 24": "Gameweek 24",
        "Regular Season - 25": "Gameweek 25",
        "Regular Season - 26": "Gameweek 26",
        "Regular Season - 27": "Gameweek 27",
        "Regular Season - 28": "Gameweek 28",
        "Regular Season - 29": "Gameweek 29",
        "Regular Season - 30": "Gameweek 30",
        "Regular Season - 31": "Gameweek 31",
        "Regular Season - 32": "Gameweek 32",
        "Regular Season - 33": "Gameweek 33",
        "Regular Season - 34": "Gameweek 34",
        "Regular Season - 35": "Gameweek 35",
        "Regular Season - 36": "Gameweek 36",
        "Regular Season - 37": "Gameweek 37",
        "Regular Season - 38": "Gameweek 38"
    }
]